{
  "type": "Program",
  "body": [
    {
      "type": "ExpressionStatement",
      "expression": {
        "type": "Literal",
        "value": "use strict",
        "raw": "'use strict'",
        "range": [
          46,
          58
        ],
        "loc": {
          "start": {
            "line": 5,
            "column": 0
          },
          "end": {
            "line": 5,
            "column": 12
          }
        }
      },
      "range": [
        46,
        59
      ],
      "loc": {
        "start": {
          "line": 5,
          "column": 0
        },
        "end": {
          "line": 5,
          "column": 13
        }
      },
      "leadingComments": [
        {
          "type": "Block",
          "value": "*\n * Created by AlexanderC on 5/25/15.\n ",
          "range": [
            0,
            44
          ],
          "loc": {
            "start": {
              "line": 1,
              "column": 0
            },
            "end": {
              "line": 3,
              "column": 3
            }
          }
        }
      ],
      "trailingComments": [
        {
          "type": "Block",
          "value": "*\n * Base exception\n ",
          "range": [
            61,
            86
          ],
          "loc": {
            "start": {
              "line": 7,
              "column": 0
            },
            "end": {
              "line": 9,
              "column": 3
            }
          }
        }
      ]
    },
    {
      "type": "ExportNamedDeclaration",
      "declaration": {
        "type": "ClassDeclaration",
        "id": {
          "type": "Identifier",
          "name": "Exception",
          "range": [
            100,
            109
          ],
          "loc": {
            "start": {
              "line": 10,
              "column": 13
            },
            "end": {
              "line": 10,
              "column": 22
            }
          }
        },
        "superClass": {
          "type": "Identifier",
          "name": "Error",
          "range": [
            118,
            123
          ],
          "loc": {
            "start": {
              "line": 10,
              "column": 31
            },
            "end": {
              "line": 10,
              "column": 36
            }
          }
        },
        "body": {
          "type": "ClassBody",
          "body": [
            {
              "type": "MethodDefinition",
              "key": {
                "type": "Identifier",
                "name": "constructor",
                "range": [
                  169,
                  180
                ],
                "loc": {
                  "start": {
                    "line": 14,
                    "column": 2
                  },
                  "end": {
                    "line": 14,
                    "column": 13
                  }
                }
              },
              "value": {
                "type": "FunctionExpression",
                "id": null,
                "params": [
                  {
                    "type": "Identifier",
                    "name": "message",
                    "range": [
                      181,
                      188
                    ],
                    "loc": {
                      "start": {
                        "line": 14,
                        "column": 14
                      },
                      "end": {
                        "line": 14,
                        "column": 21
                      }
                    }
                  }
                ],
                "body": {
                  "type": "BlockStatement",
                  "body": [
                    {
                      "type": "ExpressionStatement",
                      "expression": {
                        "type": "CallExpression",
                        "callee": {
                          "type": "Super",
                          "range": [
                            196,
                            201
                          ],
                          "loc": {
                            "start": {
                              "line": 15,
                              "column": 4
                            },
                            "end": {
                              "line": 15,
                              "column": 9
                            }
                          }
                        },
                        "arguments": [],
                        "range": [
                          196,
                          203
                        ],
                        "loc": {
                          "start": {
                            "line": 15,
                            "column": 4
                          },
                          "end": {
                            "line": 15,
                            "column": 11
                          }
                        }
                      },
                      "range": [
                        196,
                        204
                      ],
                      "loc": {
                        "start": {
                          "line": 15,
                          "column": 4
                        },
                        "end": {
                          "line": 15,
                          "column": 12
                        }
                      }
                    },
                    {
                      "type": "IfStatement",
                      "test": {
                        "type": "CallExpression",
                        "callee": {
                          "type": "MemberExpression",
                          "computed": false,
                          "object": {
                            "type": "Identifier",
                            "name": "Error",
                            "range": [
                              214,
                              219
                            ],
                            "loc": {
                              "start": {
                                "line": 17,
                                "column": 8
                              },
                              "end": {
                                "line": 17,
                                "column": 13
                              }
                            }
                          },
                          "property": {
                            "type": "Identifier",
                            "name": "hasOwnProperty",
                            "range": [
                              220,
                              234
                            ],
                            "loc": {
                              "start": {
                                "line": 17,
                                "column": 14
                              },
                              "end": {
                                "line": 17,
                                "column": 28
                              }
                            }
                          },
                          "range": [
                            214,
                            234
                          ],
                          "loc": {
                            "start": {
                              "line": 17,
                              "column": 8
                            },
                            "end": {
                              "line": 17,
                              "column": 28
                            }
                          }
                        },
                        "arguments": [
                          {
                            "type": "Literal",
                            "value": "captureStackTrace",
                            "raw": "'captureStackTrace'",
                            "range": [
                              235,
                              254
                            ],
                            "loc": {
                              "start": {
                                "line": 17,
                                "column": 29
                              },
                              "end": {
                                "line": 17,
                                "column": 48
                              }
                            }
                          }
                        ],
                        "range": [
                          214,
                          255
                        ],
                        "loc": {
                          "start": {
                            "line": 17,
                            "column": 8
                          },
                          "end": {
                            "line": 17,
                            "column": 49
                          }
                        }
                      },
                      "consequent": {
                        "type": "BlockStatement",
                        "body": [
                          {
                            "type": "ExpressionStatement",
                            "expression": {
                              "type": "CallExpression",
                              "callee": {
                                "type": "MemberExpression",
                                "computed": false,
                                "object": {
                                  "type": "Identifier",
                                  "name": "Error",
                                  "range": [
                                    265,
                                    270
                                  ],
                                  "loc": {
                                    "start": {
                                      "line": 18,
                                      "column": 6
                                    },
                                    "end": {
                                      "line": 18,
                                      "column": 11
                                    }
                                  }
                                },
                                "property": {
                                  "type": "Identifier",
                                  "name": "captureStackTrace",
                                  "range": [
                                    271,
                                    288
                                  ],
                                  "loc": {
                                    "start": {
                                      "line": 18,
                                      "column": 12
                                    },
                                    "end": {
                                      "line": 18,
                                      "column": 29
                                    }
                                  }
                                },
                                "range": [
                                  265,
                                  288
                                ],
                                "loc": {
                                  "start": {
                                    "line": 18,
                                    "column": 6
                                  },
                                  "end": {
                                    "line": 18,
                                    "column": 29
                                  }
                                }
                              },
                              "arguments": [
                                {
                                  "type": "ThisExpression",
                                  "range": [
                                    289,
                                    293
                                  ],
                                  "loc": {
                                    "start": {
                                      "line": 18,
                                      "column": 30
                                    },
                                    "end": {
                                      "line": 18,
                                      "column": 34
                                    }
                                  }
                                },
                                {
                                  "type": "MemberExpression",
                                  "computed": false,
                                  "object": {
                                    "type": "ThisExpression",
                                    "range": [
                                      295,
                                      299
                                    ],
                                    "loc": {
                                      "start": {
                                        "line": 18,
                                        "column": 36
                                      },
                                      "end": {
                                        "line": 18,
                                        "column": 40
                                      }
                                    }
                                  },
                                  "property": {
                                    "type": "Identifier",
                                    "name": "constructor",
                                    "range": [
                                      300,
                                      311
                                    ],
                                    "loc": {
                                      "start": {
                                        "line": 18,
                                        "column": 41
                                      },
                                      "end": {
                                        "line": 18,
                                        "column": 52
                                      }
                                    }
                                  },
                                  "range": [
                                    295,
                                    311
                                  ],
                                  "loc": {
                                    "start": {
                                      "line": 18,
                                      "column": 36
                                    },
                                    "end": {
                                      "line": 18,
                                      "column": 52
                                    }
                                  }
                                }
                              ],
                              "range": [
                                265,
                                312
                              ],
                              "loc": {
                                "start": {
                                  "line": 18,
                                  "column": 6
                                },
                                "end": {
                                  "line": 18,
                                  "column": 53
                                }
                              }
                            },
                            "range": [
                              265,
                              313
                            ],
                            "loc": {
                              "start": {
                                "line": 18,
                                "column": 6
                              },
                              "end": {
                                "line": 18,
                                "column": 54
                              }
                            }
                          }
                        ],
                        "range": [
                          257,
                          319
                        ],
                        "loc": {
                          "start": {
                            "line": 17,
                            "column": 51
                          },
                          "end": {
                            "line": 19,
                            "column": 5
                          }
                        }
                      },
                      "alternate": {
                        "type": "BlockStatement",
                        "body": [
                          {
                            "type": "ExpressionStatement",
                            "expression": {
                              "type": "CallExpression",
                              "callee": {
                                "type": "MemberExpression",
                                "computed": false,
                                "object": {
                                  "type": "Identifier",
                                  "name": "Object",
                                  "range": [
                                    333,
                                    339
                                  ],
                                  "loc": {
                                    "start": {
                                      "line": 20,
                                      "column": 6
                                    },
                                    "end": {
                                      "line": 20,
                                      "column": 12
                                    }
                                  }
                                },
                                "property": {
                                  "type": "Identifier",
                                  "name": "defineProperty",
                                  "range": [
                                    340,
                                    354
                                  ],
                                  "loc": {
                                    "start": {
                                      "line": 20,
                                      "column": 13
                                    },
                                    "end": {
                                      "line": 20,
                                      "column": 27
                                    }
                                  }
                                },
                                "range": [
                                  333,
                                  354
                                ],
                                "loc": {
                                  "start": {
                                    "line": 20,
                                    "column": 6
                                  },
                                  "end": {
                                    "line": 20,
                                    "column": 27
                                  }
                                }
                              },
                              "arguments": [
                                {
                                  "type": "ThisExpression",
                                  "range": [
                                    355,
                                    359
                                  ],
                                  "loc": {
                                    "start": {
                                      "line": 20,
                                      "column": 28
                                    },
                                    "end": {
                                      "line": 20,
                                      "column": 32
                                    }
                                  }
                                },
                                {
                                  "type": "Literal",
                                  "value": "stack",
                                  "raw": "'stack'",
                                  "range": [
                                    361,
                                    368
                                  ],
                                  "loc": {
                                    "start": {
                                      "line": 20,
                                      "column": 34
                                    },
                                    "end": {
                                      "line": 20,
                                      "column": 41
                                    }
                                  }
                                },
                                {
                                  "type": "ObjectExpression",
                                  "properties": [
                                    {
                                      "type": "Property",
                                      "key": {
                                        "type": "Identifier",
                                        "name": "value",
                                        "range": [
                                          380,
                                          385
                                        ],
                                        "loc": {
                                          "start": {
                                            "line": 21,
                                            "column": 8
                                          },
                                          "end": {
                                            "line": 21,
                                            "column": 13
                                          }
                                        }
                                      },
                                      "value": {
                                        "type": "MemberExpression",
                                        "computed": false,
                                        "object": {
                                          "type": "NewExpression",
                                          "callee": {
                                            "type": "Identifier",
                                            "name": "Error",
                                            "range": [
                                              392,
                                              397
                                            ],
                                            "loc": {
                                              "start": {
                                                "line": 21,
                                                "column": 20
                                              },
                                              "end": {
                                                "line": 21,
                                                "column": 25
                                              }
                                            }
                                          },
                                          "arguments": [],
                                          "range": [
                                            388,
                                            399
                                          ],
                                          "loc": {
                                            "start": {
                                              "line": 21,
                                              "column": 16
                                            },
                                            "end": {
                                              "line": 21,
                                              "column": 27
                                            }
                                          }
                                        },
                                        "property": {
                                          "type": "Identifier",
                                          "name": "stack",
                                          "range": [
                                            401,
                                            406
                                          ],
                                          "loc": {
                                            "start": {
                                              "line": 21,
                                              "column": 29
                                            },
                                            "end": {
                                              "line": 21,
                                              "column": 34
                                            }
                                          }
                                        },
                                        "range": [
                                          387,
                                          406
                                        ],
                                        "loc": {
                                          "start": {
                                            "line": 21,
                                            "column": 15
                                          },
                                          "end": {
                                            "line": 21,
                                            "column": 34
                                          }
                                        }
                                      },
                                      "kind": "init",
                                      "method": false,
                                      "shorthand": false,
                                      "computed": false,
                                      "range": [
                                        380,
                                        406
                                      ],
                                      "loc": {
                                        "start": {
                                          "line": 21,
                                          "column": 8
                                        },
                                        "end": {
                                          "line": 21,
                                          "column": 34
                                        }
                                      }
                                    }
                                  ],
                                  "range": [
                                    370,
                                    415
                                  ],
                                  "loc": {
                                    "start": {
                                      "line": 20,
                                      "column": 43
                                    },
                                    "end": {
                                      "line": 22,
                                      "column": 7
                                    }
                                  }
                                }
                              ],
                              "range": [
                                333,
                                416
                              ],
                              "loc": {
                                "start": {
                                  "line": 20,
                                  "column": 6
                                },
                                "end": {
                                  "line": 22,
                                  "column": 8
                                }
                              }
                            },
                            "range": [
                              333,
                              417
                            ],
                            "loc": {
                              "start": {
                                "line": 20,
                                "column": 6
                              },
                              "end": {
                                "line": 22,
                                "column": 9
                              }
                            }
                          }
                        ],
                        "range": [
                          325,
                          423
                        ],
                        "loc": {
                          "start": {
                            "line": 19,
                            "column": 11
                          },
                          "end": {
                            "line": 23,
                            "column": 5
                          }
                        }
                      },
                      "range": [
                        210,
                        423
                      ],
                      "loc": {
                        "start": {
                          "line": 17,
                          "column": 4
                        },
                        "end": {
                          "line": 23,
                          "column": 5
                        }
                      }
                    },
                    {
                      "type": "ExpressionStatement",
                      "expression": {
                        "type": "CallExpression",
                        "callee": {
                          "type": "MemberExpression",
                          "computed": false,
                          "object": {
                            "type": "Identifier",
                            "name": "Object",
                            "range": [
                              429,
                              435
                            ],
                            "loc": {
                              "start": {
                                "line": 25,
                                "column": 4
                              },
                              "end": {
                                "line": 25,
                                "column": 10
                              }
                            }
                          },
                          "property": {
                            "type": "Identifier",
                            "name": "defineProperty",
                            "range": [
                              436,
                              450
                            ],
                            "loc": {
                              "start": {
                                "line": 25,
                                "column": 11
                              },
                              "end": {
                                "line": 25,
                                "column": 25
                              }
                            }
                          },
                          "range": [
                            429,
                            450
                          ],
                          "loc": {
                            "start": {
                              "line": 25,
                              "column": 4
                            },
                            "end": {
                              "line": 25,
                              "column": 25
                            }
                          }
                        },
                        "arguments": [
                          {
                            "type": "ThisExpression",
                            "range": [
                              451,
                              455
                            ],
                            "loc": {
                              "start": {
                                "line": 25,
                                "column": 26
                              },
                              "end": {
                                "line": 25,
                                "column": 30
                              }
                            }
                          },
                          {
                            "type": "Literal",
                            "value": "message",
                            "raw": "'message'",
                            "range": [
                              457,
                              466
                            ],
                            "loc": {
                              "start": {
                                "line": 25,
                                "column": 32
                              },
                              "end": {
                                "line": 25,
                                "column": 41
                              }
                            }
                          },
                          {
                            "type": "ObjectExpression",
                            "properties": [
                              {
                                "type": "Property",
                                "key": {
                                  "type": "Identifier",
                                  "name": "value",
                                  "range": [
                                    476,
                                    481
                                  ],
                                  "loc": {
                                    "start": {
                                      "line": 26,
                                      "column": 6
                                    },
                                    "end": {
                                      "line": 26,
                                      "column": 11
                                    }
                                  }
                                },
                                "value": {
                                  "type": "Identifier",
                                  "name": "message",
                                  "range": [
                                    483,
                                    490
                                  ],
                                  "loc": {
                                    "start": {
                                      "line": 26,
                                      "column": 13
                                    },
                                    "end": {
                                      "line": 26,
                                      "column": 20
                                    }
                                  }
                                },
                                "kind": "init",
                                "method": false,
                                "shorthand": false,
                                "computed": false,
                                "range": [
                                  476,
                                  490
                                ],
                                "loc": {
                                  "start": {
                                    "line": 26,
                                    "column": 6
                                  },
                                  "end": {
                                    "line": 26,
                                    "column": 20
                                  }
                                }
                              }
                            ],
                            "range": [
                              468,
                              497
                            ],
                            "loc": {
                              "start": {
                                "line": 25,
                                "column": 43
                              },
                              "end": {
                                "line": 27,
                                "column": 5
                              }
                            }
                          }
                        ],
                        "range": [
                          429,
                          498
                        ],
                        "loc": {
                          "start": {
                            "line": 25,
                            "column": 4
                          },
                          "end": {
                            "line": 27,
                            "column": 6
                          }
                        }
                      },
                      "range": [
                        429,
                        499
                      ],
                      "loc": {
                        "start": {
                          "line": 25,
                          "column": 4
                        },
                        "end": {
                          "line": 27,
                          "column": 7
                        }
                      }
                    }
                  ],
                  "range": [
                    190,
                    503
                  ],
                  "loc": {
                    "start": {
                      "line": 14,
                      "column": 23
                    },
                    "end": {
                      "line": 28,
                      "column": 3
                    }
                  }
                },
                "generator": false,
                "expression": false,
                "range": [
                  180,
                  503
                ],
                "loc": {
                  "start": {
                    "line": 14,
                    "column": 13
                  },
                  "end": {
                    "line": 28,
                    "column": 3
                  }
                }
              },
              "kind": "constructor",
              "computed": false,
              "range": [
                169,
                503
              ],
              "loc": {
                "start": {
                  "line": 14,
                  "column": 2
                },
                "end": {
                  "line": 28,
                  "column": 3
                }
              },
              "leadingComments": [
                {
                  "type": "Block",
                  "value": "*\n   * @param {String} message\n   ",
                  "range": [
                    128,
                    166
                  ],
                  "loc": {
                    "start": {
                      "line": 11,
                      "column": 2
                    },
                    "end": {
                      "line": 13,
                      "column": 5
                    }
                  }
                }
              ],
              "trailingComments": [
                {
                  "type": "Block",
                  "value": "*\n   * @returns {String}\n   ",
                  "range": [
                    507,
                    539
                  ],
                  "loc": {
                    "start": {
                      "line": 30,
                      "column": 2
                    },
                    "end": {
                      "line": 32,
                      "column": 5
                    }
                  }
                }
              ],
              "static": false
            },
            {
              "type": "MethodDefinition",
              "key": {
                "type": "Identifier",
                "name": "name",
                "range": [
                  546,
                  550
                ],
                "loc": {
                  "start": {
                    "line": 33,
                    "column": 6
                  },
                  "end": {
                    "line": 33,
                    "column": 10
                  }
                }
              },
              "value": {
                "type": "FunctionExpression",
                "id": null,
                "params": [],
                "body": {
                  "type": "BlockStatement",
                  "body": [
                    {
                      "type": "ReturnStatement",
                      "argument": {
                        "type": "MemberExpression",
                        "computed": false,
                        "object": {
                          "type": "MemberExpression",
                          "computed": false,
                          "object": {
                            "type": "ThisExpression",
                            "range": [
                              566,
                              570
                            ],
                            "loc": {
                              "start": {
                                "line": 34,
                                "column": 11
                              },
                              "end": {
                                "line": 34,
                                "column": 15
                              }
                            }
                          },
                          "property": {
                            "type": "Identifier",
                            "name": "constructor",
                            "range": [
                              571,
                              582
                            ],
                            "loc": {
                              "start": {
                                "line": 34,
                                "column": 16
                              },
                              "end": {
                                "line": 34,
                                "column": 27
                              }
                            }
                          },
                          "range": [
                            566,
                            582
                          ],
                          "loc": {
                            "start": {
                              "line": 34,
                              "column": 11
                            },
                            "end": {
                              "line": 34,
                              "column": 27
                            }
                          }
                        },
                        "property": {
                          "type": "Identifier",
                          "name": "name",
                          "range": [
                            583,
                            587
                          ],
                          "loc": {
                            "start": {
                              "line": 34,
                              "column": 28
                            },
                            "end": {
                              "line": 34,
                              "column": 32
                            }
                          }
                        },
                        "range": [
                          566,
                          587
                        ],
                        "loc": {
                          "start": {
                            "line": 34,
                            "column": 11
                          },
                          "end": {
                            "line": 34,
                            "column": 32
                          }
                        }
                      },
                      "range": [
                        559,
                        588
                      ],
                      "loc": {
                        "start": {
                          "line": 34,
                          "column": 4
                        },
                        "end": {
                          "line": 34,
                          "column": 33
                        }
                      }
                    }
                  ],
                  "range": [
                    553,
                    592
                  ],
                  "loc": {
                    "start": {
                      "line": 33,
                      "column": 13
                    },
                    "end": {
                      "line": 35,
                      "column": 3
                    }
                  }
                },
                "generator": false,
                "expression": false,
                "range": [
                  550,
                  592
                ],
                "loc": {
                  "start": {
                    "line": 33,
                    "column": 10
                  },
                  "end": {
                    "line": 35,
                    "column": 3
                  }
                }
              },
              "kind": "get",
              "computed": false,
              "range": [
                542,
                592
              ],
              "loc": {
                "start": {
                  "line": 33,
                  "column": 2
                },
                "end": {
                  "line": 35,
                  "column": 3
                }
              },
              "leadingComments": [
                {
                  "type": "Block",
                  "value": "*\n   * @returns {String}\n   ",
                  "range": [
                    507,
                    539
                  ],
                  "loc": {
                    "start": {
                      "line": 30,
                      "column": 2
                    },
                    "end": {
                      "line": 32,
                      "column": 5
                    }
                  }
                }
              ],
              "static": false
            }
          ],
          "range": [
            124,
            594
          ],
          "loc": {
            "start": {
              "line": 10,
              "column": 37
            },
            "end": {
              "line": 36,
              "column": 1
            }
          }
        },
        "range": [
          94,
          594
        ],
        "loc": {
          "start": {
            "line": 10,
            "column": 7
          },
          "end": {
            "line": 36,
            "column": 1
          }
        },
        "leadingComments": [
          {
            "type": "Block",
            "value": "*\n * Base exception\n ",
            "range": [
              61,
              86
            ],
            "loc": {
              "start": {
                "line": 7,
                "column": 0
              },
              "end": {
                "line": 9,
                "column": 3
              }
            }
          }
        ],
        "trailingComments": []
      },
      "specifiers": [],
      "source": null,
      "range": [
        87,
        594
      ],
      "loc": {
        "start": {
          "line": 10,
          "column": 0
        },
        "end": {
          "line": 36,
          "column": 1
        }
      },
      "leadingComments": [
        {
          "type": "Block",
          "value": "*\n * Base exception\n ",
          "range": [
            61,
            86
          ],
          "loc": {
            "start": {
              "line": 7,
              "column": 0
            },
            "end": {
              "line": 9,
              "column": 3
            }
          }
        }
      ]
    }
  ],
  "sourceType": "module",
  "range": [
    46,
    594
  ],
  "loc": {
    "start": {
      "line": 5,
      "column": 0
    },
    "end": {
      "line": 36,
      "column": 1
    }
  },
  "comments": [
    {
      "type": "Block",
      "value": "*\n * Created by AlexanderC on 5/25/15.\n ",
      "range": [
        0,
        44
      ],
      "loc": {
        "start": {
          "line": 1,
          "column": 0
        },
        "end": {
          "line": 3,
          "column": 3
        }
      }
    },
    {
      "type": "Block",
      "value": "*\n * Base exception\n ",
      "range": [
        61,
        86
      ],
      "loc": {
        "start": {
          "line": 7,
          "column": 0
        },
        "end": {
          "line": 9,
          "column": 3
        }
      }
    },
    {
      "type": "Block",
      "value": "*\n   * @param {String} message\n   ",
      "range": [
        128,
        166
      ],
      "loc": {
        "start": {
          "line": 11,
          "column": 2
        },
        "end": {
          "line": 13,
          "column": 5
        }
      }
    },
    {
      "type": "Block",
      "value": "*\n   * @returns {String}\n   ",
      "range": [
        507,
        539
      ],
      "loc": {
        "start": {
          "line": 30,
          "column": 2
        },
        "end": {
          "line": 32,
          "column": 5
        }
      }
    }
  ]
}